test_python_project_example_202412/__init__.py
test_python_project_example_202412-0.2.0.dist-info/METADATA
test_python_project_example_202412-0.2.0.dist-info/WHEEL
test_python_project_example_202412-0.2.0.dist-info/top_level.txt
test_python_project_example_202412-0.2.0.dist-info/RECORD
