Metadata-Version: 2.1
Name: test-python-project-example-202412
Version: 0.2.0
Summary: Test python project example
